rihog/__init__.py
rihog/rihog.py
rihog/test/__init__.py
rihog/test/test_rihog.py
rihog-1.0.2.dist-info/METADATA
rihog-1.0.2.dist-info/WHEEL
rihog-1.0.2.dist-info/licenses/LICENSE
rihog-1.0.2.dist-info/RECORD
