Metadata-Version: 2.4
Name: rihog
Version: 1.0.2
Summary: Vectorized PyTorch implementation of Rotation Invariant Histogram of Oriented Gradients.
Project-URL: Homepage, https://github.com/DSAureli/rihog
Project-URL: Issues, https://github.com/DSAureli/rihog/issues
Author: Davide Nanni
License-Expression: MIT
License-File: LICENSE
Classifier: Development Status :: 5 - Production/Stable
Classifier: Environment :: GPU
Classifier: Intended Audience :: Science/Research
Classifier: License :: OSI Approved :: MIT License
Classifier: Operating System :: OS Independent
Classifier: Programming Language :: Python :: 3 :: Only
Classifier: Topic :: Scientific/Engineering :: Image Processing
Requires-Python: >=3.11
Requires-Dist: einops
Requires-Dist: torch
